{
  "matematica": [
    {
      "habilidade": "H01A",
      "media_delta": -0.051,
      "cohen_d": -0.107,
      "disciplina": "Matemática"
    },
    {
      "habilidade": "H02A",
      "media_delta": 0.012,
      "cohen_d": 0.032,
      "disciplina": "Matemática"
    },
    {
      "habilidade": "H02B",
      "media_delta": 0.107,
      "cohen_d": 0.292,
      "disciplina": "Matemática"
    },
    {
      "habilidade": "H03A",
      "media_delta": 0.004,
      "cohen_d": 0.01,
      "disciplina": "Matemática"
    },
    {
      "habilidade": "H03B",
      "media_delta": 0.159,
      "cohen_d": 0.385,
      "disciplina": "Matemática"
    },
    {
      "habilidade": "H04A",
      "media_delta": -0.018,
      "cohen_d": -0.038,
      "disciplina": "Matemática"
    },
    {
      "habilidade": "H05B",
      "media_delta": -0.085,
      "cohen_d": -0.171,
      "disciplina": "Matemática"
    },
    {
      "habilidade": "H06A",
      "media_delta": -0.066,
      "cohen_d": -0.184,
      "disciplina": "Matemática"
    },
    {
      "habilidade": "H06B",
      "media_delta": -0.049,
      "cohen_d": -0.132,
      "disciplina": "Matemática"
    },
    {
      "habilidade": "H07A",
      "media_delta": -0.183,
      "cohen_d": -0.392,
      "disciplina": "Matemática"
    },
    {
      "habilidade": "H08A",
      "media_delta": -0.095,
      "cohen_d": -0.2,
      "disciplina": "Matemática"
    },
    {
      "habilidade": "H09A",
      "media_delta": 0.201,
      "cohen_d": 0.375,
      "disciplina": "Matemática"
    },
    {
      "habilidade": "H10A",
      "media_delta": -0.25,
      "cohen_d": -0.461,
      "disciplina": "Matemática"
    },
    {
      "habilidade": "H11A",
      "media_delta": -0.043,
      "cohen_d": -0.12,
      "disciplina": "Matemática"
    },
    {
      "habilidade": "H11B",
      "media_delta": -0.004,
      "cohen_d": -0.009,
      "disciplina": "Matemática"
    },
    {
      "habilidade": "H12A",
      "media_delta": 0.123,
      "cohen_d": 0.299,
      "disciplina": "Matemática"
    },
    {
      "habilidade": "H12B",
      "media_delta": -0.025,
      "cohen_d": -0.081,
      "disciplina": "Matemática"
    },
    {
      "habilidade": "H13A",
      "media_delta": -0.168,
      "cohen_d": -0.409,
      "disciplina": "Matemática"
    },
    {
      "habilidade": "H13B",
      "media_delta": -0.011,
      "cohen_d": -0.044,
      "disciplina": "Matemática"
    },
    {
      "habilidade": "H14A",
      "media_delta": -0.089,
      "cohen_d": -0.172,
      "disciplina": "Matemática"
    },
    {
      "habilidade": "H15A",
      "media_delta": 0.113,
      "cohen_d": 0.287,
      "disciplina": "Matemática"
    },
    {
      "habilidade": "H15B",
      "media_delta": -0.014,
      "cohen_d": -0.049,
      "disciplina": "Matemática"
    },
    {
      "habilidade": "H16A",
      "media_delta": -0.144,
      "cohen_d": -0.29,
      "disciplina": "Matemática"
    },
    {
      "habilidade": "H17A",
      "media_delta": -0.013,
      "cohen_d": -0.031,
      "disciplina": "Matemática"
    },
    {
      "habilidade": "H18B",
      "media_delta": -0.134,
      "cohen_d": -0.264,
      "disciplina": "Matemática"
    },
    {
      "habilidade": "H19A",
      "media_delta": -0.207,
      "cohen_d": -0.468,
      "disciplina": "Matemática"
    },
    {
      "habilidade": "H19B",
      "media_delta": -0.031,
      "cohen_d": -0.117,
      "disciplina": "Matemática"
    },
    {
      "habilidade": "H20A",
      "media_delta": -0.066,
      "cohen_d": -0.178,
      "disciplina": "Matemática"
    },
    {
      "habilidade": "H20B",
      "media_delta": -0.1,
      "cohen_d": -0.264,
      "disciplina": "Matemática"
    },
    {
      "habilidade": "H21A",
      "media_delta": -0.007,
      "cohen_d": -0.019,
      "disciplina": "Matemática"
    },
    {
      "habilidade": "H21B",
      "media_delta": 0.001,
      "cohen_d": 0.002,
      "disciplina": "Matemática"
    },
    {
      "habilidade": "H22A",
      "media_delta": -0.097,
      "cohen_d": -0.243,
      "disciplina": "Matemática"
    },
    {
      "habilidade": "H22B",
      "media_delta": 0.012,
      "cohen_d": 0.05,
      "disciplina": "Matemática"
    },
    {
      "habilidade": "H23B",
      "media_delta": -0.024,
      "cohen_d": -0.086,
      "disciplina": "Matemática"
    },
    {
      "habilidade": "H24A",
      "media_delta": -0.058,
      "cohen_d": -0.162,
      "disciplina": "Matemática"
    },
    {
      "habilidade": "H25B",
      "media_delta": 0.076,
      "cohen_d": 0.252,
      "disciplina": "Matemática"
    },
    {
      "habilidade": "H26A",
      "media_delta": -0.001,
      "cohen_d": -0.002,
      "disciplina": "Matemática"
    }
  ],
  "portugues": [
    {
      "habilidade": "H01R",
      "media_delta": -0.359,
      "cohen_d": -0.573,
      "disciplina": "Língua Portuguesa"
    },
    {
      "habilidade": "H02A",
      "media_delta": 0.044,
      "cohen_d": 0.118,
      "disciplina": "Língua Portuguesa"
    },
    {
      "habilidade": "H02R",
      "media_delta": -0.122,
      "cohen_d": -0.313,
      "disciplina": "Língua Portuguesa"
    },
    {
      "habilidade": "H03R",
      "media_delta": -0.09,
      "cohen_d": -0.172,
      "disciplina": "Língua Portuguesa"
    },
    {
      "habilidade": "H04A",
      "media_delta": -0.16,
      "cohen_d": -0.39,
      "disciplina": "Língua Portuguesa"
    },
    {
      "habilidade": "H04R",
      "media_delta": 0.007,
      "cohen_d": 0.02,
      "disciplina": "Língua Portuguesa"
    },
    {
      "habilidade": "H05R",
      "media_delta": -0.216,
      "cohen_d": -0.273,
      "disciplina": "Língua Portuguesa"
    },
    {
      "habilidade": "H06A",
      "media_delta": -0.081,
      "cohen_d": -0.215,
      "disciplina": "Língua Portuguesa"
    },
    {
      "habilidade": "H06R",
      "media_delta": -0.152,
      "cohen_d": -0.374,
      "disciplina": "Língua Portuguesa"
    },
    {
      "habilidade": "H07A",
      "media_delta": -0.094,
      "cohen_d": -0.274,
      "disciplina": "Língua Portuguesa"
    },
    {
      "habilidade": "H07R",
      "media_delta": -0.152,
      "cohen_d": -0.367,
      "disciplina": "Língua Portuguesa"
    },
    {
      "habilidade": "H08A",
      "media_delta": -0.137,
      "cohen_d": -0.238,
      "disciplina": "Língua Portuguesa"
    },
    {
      "habilidade": "H09A",
      "media_delta": -0.095,
      "cohen_d": -0.26,
      "disciplina": "Língua Portuguesa"
    },
    {
      "habilidade": "H09R",
      "media_delta": -0.087,
      "cohen_d": -0.217,
      "disciplina": "Língua Portuguesa"
    },
    {
      "habilidade": "H10A",
      "media_delta": -0.165,
      "cohen_d": -0.273,
      "disciplina": "Língua Portuguesa"
    },
    {
      "habilidade": "H11A",
      "media_delta": -0.104,
      "cohen_d": -0.2,
      "disciplina": "Língua Portuguesa"
    },
    {
      "habilidade": "H12A",
      "media_delta": -0.146,
      "cohen_d": -0.277,
      "disciplina": "Língua Portuguesa"
    },
    {
      "habilidade": "H12R",
      "media_delta": 0.012,
      "cohen_d": 0.039,
      "disciplina": "Língua Portuguesa"
    },
    {
      "habilidade": "H13A",
      "media_delta": -0.095,
      "cohen_d": -0.249,
      "disciplina": "Língua Portuguesa"
    },
    {
      "habilidade": "H13R",
      "media_delta": -0.032,
      "cohen_d": -0.095,
      "disciplina": "Língua Portuguesa"
    },
    {
      "habilidade": "H14A",
      "media_delta": 0.01,
      "cohen_d": 0.029,
      "disciplina": "Língua Portuguesa"
    },
    {
      "habilidade": "H14R",
      "media_delta": -0.078,
      "cohen_d": -0.205,
      "disciplina": "Língua Portuguesa"
    },
    {
      "habilidade": "H15A",
      "media_delta": -0.113,
      "cohen_d": -0.174,
      "disciplina": "Língua Portuguesa"
    },
    {
      "habilidade": "H16A",
      "media_delta": -0.045,
      "cohen_d": -0.143,
      "disciplina": "Língua Portuguesa"
    },
    {
      "habilidade": "H16R",
      "media_delta": -0.062,
      "cohen_d": -0.174,
      "disciplina": "Língua Portuguesa"
    },
    {
      "habilidade": "H17A",
      "media_delta": -0.106,
      "cohen_d": -0.218,
      "disciplina": "Língua Portuguesa"
    },
    {
      "habilidade": "H18A",
      "media_delta": -0.003,
      "cohen_d": -0.006,
      "disciplina": "Língua Portuguesa"
    },
    {
      "habilidade": "H18R",
      "media_delta": -0.101,
      "cohen_d": -0.195,
      "disciplina": "Língua Portuguesa"
    },
    {
      "habilidade": "H19A",
      "media_delta": -0.148,
      "cohen_d": -0.291,
      "disciplina": "Língua Portuguesa"
    },
    {
      "habilidade": "H20R",
      "media_delta": 0.098,
      "cohen_d": 0.256,
      "disciplina": "Língua Portuguesa"
    }
  ]
}